rff/__init__.py
rff/dataloader.py
rff/functional.py
rff/layers.py
random_fourier_features_pytorch-1.0.1.dist-info/LICENSE
random_fourier_features_pytorch-1.0.1.dist-info/METADATA
random_fourier_features_pytorch-1.0.1.dist-info/WHEEL
random_fourier_features_pytorch-1.0.1.dist-info/top_level.txt
random_fourier_features_pytorch-1.0.1.dist-info/RECORD
