Metadata-Version: 2.1
Name: random-fourier-features-pytorch
Version: 1.0.1
Summary: Random Fourier Features for PyTorch
Home-page: https://github.com/jmclong/random-fourier-features-pytorch
Author: Joshua Long
Author-email: joshualong@live.com
License: MIT
License-File: LICENSE
Requires-Dist: numpy (>=1.17)
Requires-Dist: torch (>=1.7)
Requires-Dist: torchvision (>=0.9)
